{
  "fingerprint": "621ca031",
  "trigger": "Phase_cost_sensitivity",
  "pattern": "cost_sensitivity",
  "detail": "{'verdict': 'FAIL', 'base_annual': 0.08968973598337077, 'stressed_annual': 0.03260213292094438, 'decay_pct': 0.6365009600765343, 'threshold': 0.5}",
  "fix": "Strategy too sensitive to trading costs. Reduce turnover (longer rebalance interval, fewer stocks) or find stronger alpha to absorb cost drag.",
  "hit_count": 13,
  "first_seen": "2026-06-24",
  "last_seen": "2026-06-28",
  "strategies": [
    "small_cap_factor__window20",
    "autoresearch_7258f152",
    "autoresearch_4063f1c4",
    "autoresearch_fb43fa16",
    "autoresearch_a23f4dde",
    "autoresearch_69ede240",
    "autoresearch_58ad0efc",
    "close_position__n5",
    "autoresearch_6332599c"
  ]
}